{
  "application": {
    "name": "INZFS",
    "sections": [
      {
        "title": "Proposal Summary",
        "tag": "proposal-summary",
        "url": "proposal-summary-overview",
        "returnToSummaryPageLinkText": "Return to the proposal summary overview",
        "continueButtonText": "Save and continue to next question",
        "RazorView": "ProposalSummaryOverview",
        "pages": [
          {
            "name": "project-name",
            "question": "4.1. Project Name",
            "titleQuestion": "4.1. What is the name of your project?",
            "description": "Description",
            "errorMessage": "Please entre a valid project name",
            "fieldType": "gdsTextBox",
            "friendlyFieldName": "Project Name",
            "fieldName": "project-name",
            "mandatory": true,
            "accordianReference": "",
            "maxLength": 50,
            "maxLengthValidationType": "Character",
            "showMarkComplete": true,
            "showSaveProgessButton": true
          },
          {
            "name": "estimated-start-date",
            "question": "4.2. Estimated start date",
            "titleQuestion": "4.2. When do you estimate the project will start?",
            "description": "Description",
            "errorMessage": "Select a Valid Date",
            "fieldType": "gdsDateBox",
            "friendlyFieldName": "Estimated Start Date",
            "fieldName": "estimated-start-date",
            "mandatory": true,
            "showMarkComplete": true,
            "showSaveProgessButton": true
          },
          {
            "name": "estimated-end-date",
            "question": "4.3. Estimated end date",
            "titleQuestion": "4.3. When do you estimate the project will end?",
            "description": "Description",
            "errorMessage": "Select a Valid Date",
            "fieldType": "gdsDateBox",
            "friendlyFieldName": "Estimated End Date",
            "fieldName": "estimated-end-date",
            "mandatory": true,
            "showMarkComplete": true,
            "showSaveProgessButton": true
          },
          {
            "name": "project-location",
            "question": "4.4. Project Location",
            "titleQuestion": "4.4. Will your project be mainly carried out at your organisation's registered address?",
            "description": "Description",
            "errorMessage": "Select Yes or No",
            "fieldType": "gdsSingleLineRadio",
            "friendlyFieldName": "Technology Readiness Level",
            "fieldName": "business-technology-readiness",
            "mandatory": true,
            "accordianReference": "",
            "showMarkComplete": true,
            "showSaveProgessButton": true
          },
          {
            "name": "project-summary",
            "question": "4.5. Project Summary",
            "description": "Description",
            "errorMessage": "Enter project summary details",
            "fieldType": "gdsTextArea",
            "friendlyFieldName": "Project Summary",
            "fieldName": "project-summary",
            "mandatory": true,
            "accordianReference": "",
            "maxLength": 1000,
            "maxLengthValidationType": "Character",
            "hint": "This should be a brief description to help introduce your project to assessors",
            "showMarkComplete": true,
            "showSaveProgessButton": true
          },
          {
            "name": "grant-justification",
            "question": "4.6. Grant Justification",
            "description": "Description",
            "errorMessage": "Entre Grant Justification",
            "fieldType": "gdsTextArea",
            "friendlyFieldName": "Grant Justification",
            "fieldName": "grant-justification",
            "mandatory": true,
            "accordianReference": "",
            "maxLength": 1000,
            "maxLengthValidationType": "Character",
            "hint": "Explain why public sector funding is required to take this concept forward.",
            "showMarkComplete": true,
            "showSaveProgessButton": true
          }
        ]
      },
      {
        "title": "Business Proposal",
        "tag": "business-proposal",
        "url": "business-proposal-overview",
        "returnToSummaryPageLinkText": "Return to the business proposal overview",
        "continueButtonText": "Save and continue to next question",
        "RazorView": "BusinessProposalOverview",
        "pages": [
          {
            "name": "business-proposal",
            "question": "5.1. Proposal",
            "description": "Description",
            "errorMessage": "Enter business proposal",
            "fieldType": "gdsTextArea",
            "friendlyFieldName": "Business proposal",
            "fieldName": "business-proposal",
            "mandatory": true,
            "accordianReference": "",
            "maxLength": 1000,
            "maxLengthValidationType": "Character",
            "hint": "",
            "showMarkComplete": true,
            "showSaveProgessButton": true
          },
          {
            "name": "business-proposal-file",
            "question": "5.1. Proposal",
            "description": "Description",
            "errorMessage": "Enter business proposal",
            "fieldType": "gdsFileUpload",
            "friendlyFieldName": "Business proposal",
            "fieldName": "business-proposal-file",
            "mandatory": true,
            "accordianReference": "",
            "showMarkComplete": true,
            "showSaveProgessButton": true,
            "filetoDownload" : ""
          },
          {
            "name": "business-plan",
            "question": "5.2. Business Plan",
            "description": "Description",
            "errorMessage": "Enter business plan",
            "fieldType": "gdsTextArea",
            "friendlyFieldName": "Business plan",
            "fieldName": "business-plan",
            "mandatory": true,
            "accordianReference": "",
            "maxLength": 1000,
            "maxLengthValidationType": "Character",
            "showMarkComplete": true,
            "showSaveProgessButton": true
          },
          {
            "name": "business-technology-readiness",
            "question": "5.3. Technology Readiness Level (TRL)",
            "description": "Description",
            "errorMessage": "Enter technology readiness level",
            "fieldType": "gdsTextArea",
            "friendlyFieldName": "Technology Readiness Level",
            "fieldName": "business-technology-readiness",
            "mandatory": true,
            "accordianReference": "",
            "maxLength": 1000,
            "maxLengthValidationType": "Character",
            "showMarkComplete": true,
            "showSaveProgessButton": true
          },
          {
            "name": "business-infrastructure",
            "question": "5.4. Infrastructure",
            "description": "Description",
            "errorMessage": "Enter infrastructure",
            "fieldType": "gdsTextArea",
            "friendlyFieldName": "Infrastructure",
            "fieldName": "business-infrastructure",
            "mandatory": true,
            "accordianReference": "",
            "maxLength": 1000,
            "maxLengthValidationType": "Character",
            "hint": "You should include evidence where you can.",
            "showMarkComplete": true,
            "showSaveProgessButton": true
          },
          {
            "name": "business-environmental-impact",
            "question": "5.5. Environmental impact",
            "description": "Description",
            "errorMessage": "Enter environmental impact",
            "fieldType": "gdsTextArea",
            "friendlyFieldName": "Environmental impact",
            "fieldName": "business-environmental-impact",
            "mandatory": true,
            "accordianReference": "",
            "maxLength": 1000,
            "maxLengthValidationType": "Character",
            "showMarkComplete": true,
            "showSaveProgessButton": true
          },
          {
            "name": "business-regulations",
            "question": "5.6. Regulations",
            "description": "Description",
            "errorMessage": "Enter regulations",
            "fieldType": "gdsTextArea",
            "friendlyFieldName": "Regulations",
            "fieldName": "business-regulations",
            "mandatory": true,
            "accordianReference": "",
            "maxLength": 1000,
            "maxLengthValidationType": "Character",
            "showMarkComplete": true,
            "showSaveProgessButton": true
          },
          {
            "name": "business-impact-on-climate-change",
            "question": "5.7. Impact on climate change",
            "description": "Description",
            "errorMessage": "Enter impact on climate change",
            "fieldType": "gdsTextArea",
            "friendlyFieldName": "Impact on climate change",
            "fieldName": "business-impact-on-climate-change",
            "mandatory": true,
            "accordianReference": "",
            "maxLength": 1000,
            "maxLengthValidationType": "Character",
            "hint": "Use scientific studies and research to prove your claims where you can.",
            "showMarkComplete": true,
            "showSaveProgessButton": true
          },
          {
            "name": "business-project-plan",
            "question": "5.8. Project plan",
            "description": "Description",
            "errorMessage": "Enter project plan",
            "fieldType": "gdsTextArea",
            "friendlyFieldName": "Project plan",
            "fieldName": "business-project-plan",
            "mandatory": true,
            "accordianReference": "",
            "maxLength": 1000,
            "maxLengthValidationType": "Character",
            "hint": "Use scientific studies and research to prove your claims where you can.",
            "showMarkComplete": true,
            "showSaveProgessButton": true
          },
          {
            "name": "business-project-evaluation",
            "question": "5.9. Project evaluation",
            "description": "Description",
            "errorMessage": "Enter project evaluation",
            "fieldType": "gdsTextArea",
            "friendlyFieldName": "Project evaluation",
            "fieldName": "business-project-evaluation",
            "mandatory": true,
            "accordianReference": "",
            "maxLength": 1000,
            "maxLengthValidationType": "Character",
            "hint": "Use scientific studies and research to prove your claims where you can.",
            "showMarkComplete": true,
            "showSaveProgessButton": true
          }
        ]
      },
      {
        "title": "Finance Proposal",
        "tag": "finance-proposal",
        "url": "finance-proposal-overview",
        "returnToSummaryPageLinkText": "Return to the finance proposal overview",
        "continueButtonText": "Save and continue to next question",
        "RazorView": "FinanceProposalOverview",
        "pages": [
          {
            "name": "project-cost-breakdown",
            "question": "6.1. Project cost breakdown",
            "titleQuestion": "6.1 Project cost breakdown",
            "description": "Provide a breakdown of your costs using the template provided in the download section of this page.",
            "errorMessage": "Please provide a breakdown of your costs",
            "fieldType": "gdsFileUpload",
            "friendlyFieldName": "Project Cost Breakdown",
            "fieldName": "project-cost-breakdown",
            "mandatory": true,
            "accordianReference": "",
            "maxLength": 50,
            "maxLengthValidationType": "Character",
            "showMarkComplete": true,
            "showSaveProgessButton": true
          },
          {
            "name": "summarise-project-spend",
            "question": "6.2. Summarise project spend areas",
            "titleQuestion": "6.2 Summarise the main areas of spend within this project",
            "description": "Description",
            "errorMessage": "Please provide a summary of the main areas of spend within this project",
            "fieldType": "gdsTextArea",
            "friendlyFieldName": "Summarise Project Spend",
            "fieldName": "summarise-project-spend",
            "maxLength": 1000,
            "maxLengthValidationType": "Word",
            "mandatory": true,
            "showMarkComplete": true,
            "showSaveProgessButton": true
          },
          {
            "name": "summarise-spend-history",
            "question": "6.3. Summarise your spending history",
            "titleQuestion": "6.3 Summarise the main areas of spend within this project",
            "description": "Description",
            "errorMessage": "Please provide a summary of your spending history",
            "fieldType": "gdsTextArea",
            "friendlyFieldName": "Summarise Spending History",
            "maxLength": 1000,
            "maxLengthValidationType": "Word",
            "fieldName": "summarise-spend-history",
            "mandatory": true,
            "showMarkComplete": true,
            "showSaveProgessButton": true
          },
          {
            "name": "further-project-funding",
            "question": "6.4. Any further project funding",
            "titleQuestion": "6.4. Any further project funding",
            "description": "Description",
            "errorMessage": "Enter any other funding details",
            "fieldType": "gdsTextArea",
            "friendlyFieldName": "Further Project Funding",
            "maxLength": 1000,
            "maxLengthValidationType": "Character",
            "fieldName": "further-project-funding",
            "mandatory": true,
            "accordianReference": "",
            "showMarkComplete": true,
            "showSaveProgessButton": true
          },
          {
            "name": "experience-and-supply-chain",
            "question": "6.5. Experience and supply chain",
            "description": "Description",
            "errorMessage": "Enter details about your experience and supply chain",
            "fieldType": "gdsTextArea",
            "friendlyFieldName": "Experience and supply chain",
            "fieldName": "experience-and-supply-chain",
            "mandatory": true,
            "accordianReference": "",
            "maxLength": 1000,
            "maxLengthValidationType": "Word",
            "showMarkComplete": true,
            "showSaveProgessButton": true
          },
          {
            "name": "overhead-calculations",
            "question": "6.6. Overhead calculations",
            "description": "Description",
            "errorMessage": "Entre your overhead calculations",
            "fieldType": "gdsTextArea",
            "friendlyFieldName": "Overhead calculations",
            "fieldName": "overhead-calculations",
            "mandatory": true,
            "accordianReference": "",
            "maxLength": 1000,
            "maxLengthValidationType": "Word",
            "showMarkComplete": true,
            "showSaveProgessButton": true
          }
        ]
      }
    ]

  }
}
