{
  "application": {
    "name": "INZFS",
    "sections": [
      {
        "title": "Confirm your eligibility",
        "overviewTitle": "1. Confirm your eligibility",
        "tag": "confirm-your-eligibility",
        "url": "confirm-your-eligibility",
        "continueButtonText": "Save and continue",
        "RazorView": "ConfirmYourEligibility",
        "pages": [

        ]
      },
      {
        "title": "Your organisation",
        "overviewTitle": "2. Your organisation",
        "tag": "your-organisation",
        "url": "your-organisation",
        "returnToSummaryPageLinkText": "Return to the proposal summary overview",
        "continueButtonText": "Save and continue",
        "RazorView": "YourOrganisation",
        "pages": [
          {
            "name": "full-name",
            "question": "Full Name",
            "titleQuestion": "What is your full name?",
            "description": "Description",
            "errorMessage": "Please enter full name ",
            "fieldType": "gdsTextBox",
            "friendlyFieldName": "Full Name",
            "fieldName": "full-name",
            "mandatory": true,
            "accordianReference": "",
            "maxLength": 50,
            "maxLengthValidationType": "Character",
            "showMarkComplete": true,
            "showSaveProgessButton": true
          },
          {
            "name": "job-title",
            "question": "Job Title",
            "titleQuestion": "What is your job title?",
            "description": "Description",
            "errorMessage": "Please enter your job title ",
            "fieldType": "gdsTextBox",
            "friendlyFieldName": "Job Title",
            "fieldName": "job-title",
            "mandatory": true,
            "accordianReference": "",
            "maxLength": 50,
            "maxLengthValidationType": "Character",
            "showMarkComplete": true,
            "showSaveProgessButton": true
          },
          {
            "name": "organisation-running",
            "question": "Organisation Running",
            "titleQuestion": "Is your organisation more than 1 year old?",
            "hint": "If your organisation is less than one year old you don't have to enter any further information on this page.",
            "errorMessage": "Select Yes or No",
            "fieldType": "gdsYesorNoRadio",
            "friendlyFieldName": "Organisation Running",
            "fieldName": "organisation-running",
            "mandatory": true,
            "accordianReference": "",
            "showMarkComplete": false,
            "showSaveProgessButton": false,
            "displayQuestionCounter": true,
            "previousPage": {
              "link": "Back to consortium applicants",
              "text": "application-overview"
            }
          },
          {
            "name": "recent-turnover",
            "question": "Most recent annual turnover",
            "hint": "The amount of money your business has taken over a period of 12 months.",
            "description": "Description",
            "errorMessage": "Please enter 12 month turnover value",
            "fieldType": "gdsCurrencyBox",
            "friendlyFieldName": "Recent Turnover",
            "fieldName": "recent-turnover",
            "mandatory": true,
            "accordianReference": "",
            "maxLength": 50,
            "maxLengthValidationType": "Character",
            "showMarkComplete": true,
            "showSaveProgessButton": true
          },
          {
            "name": "recent-turnover-date",
            "question": "Most recent turnover date",
            "description": "Description",
            "errorMessage": "Select a valid date",
            "fieldType": "gdsDateBox",
            "friendlyFieldName": "Most recent turnover date",
            "fieldName": "recent-turnover-date",
            "mandatory": true,
            "showMarkComplete": true,
            "showSaveProgessButton": true
          },
          {
            "name": "balance-sheet-total",
            "question": "Balance sheet total",
            "hint": "Amount, in pounds",
            "description": "Description",
            "errorMessage": "Please enter balance sheet total",
            "fieldType": "gdsCurrencyBox",
            "friendlyFieldName": "Balance sheet total",
            "fieldName": "balance-sheet-total",
            "mandatory": true,
            "accordianReference": "",
            "maxLength": 50,
            "maxLengthValidationType": "Character",
            "showMarkComplete": true,
            "showSaveProgessButton": true
          },
          {
            "name": "balance-sheet-date",
            "question": "Balance sheet date",
            "description": "Description",
            "errorMessage": "Select a Valid Date",
            "fieldType": "gdsDateBox",
            "friendlyFieldName": "Balance sheet date",
            "fieldName": "balance-sheet-date",
            "mandatory": true,
            "showMarkComplete": true,
            "showSaveProgessButton": true
          },
          {
            "name": "vat-recovery",
            "question": "Vat Recovery",
            "titleQuestion": "Is your organisation VAT registered?",
            "errorMessage": "Select Yes or No",
            "fieldType": "gdsYesorNoRadio",
            "friendlyFieldName": "Vat Recovery",
            "fieldName": "vat-recovery",
            "mandatory": true,
            "accordianReference": "",
            "showMarkComplete": false,
            "showSaveProgessButton": false,
            "displayQuestionCounter": true
          },
          {
            "name": "organisation-name",
            "question": "Organisation Name",
            "description": "Description",
            "errorMessage": "Please enter organisation name",
            "fieldType": "gdsTextBox",
            "friendlyFieldName": "Organisation Name",
            "fieldName": "organisation-name",
            "mandatory": true,
            "accordianReference": "",
            "maxLength": 50,
            "maxLengthValidationType": "Character",
            "showMarkComplete": true,
            "showSaveProgessButton": true
          },
          {
            "name": "organisation-website",
            "question": "Organisation Website",
            "description": "Description",
            "errorMessage": "Please enter organisation name website",
            "fieldType": "gdsTextBox",
            "friendlyFieldName": "Organisation Website",
            "fieldName": "organisation-website",
            "mandatory": true,
            "accordianReference": "",
            "maxLength": 50,
            "maxLengthValidationType": "Character",
            "showMarkComplete": true,
            "showSaveProgessButton": true
          },
          {
            "name": "organisation-address",
            "question": "Organisation Address",
            "titleQuestion": "What is your organisation's registered address?",
            "description": "Description",
            "errorMessage": "Please enter organisation name website",
            "fieldType": "gdsTextBox",
            "friendlyFieldName": "Organisation Address",
            "fieldName": "organisation-address",
            "mandatory": true,
            "accordianReference": "",
            "maxLength": 50,
            "maxLengthValidationType": "Character",
            "showMarkComplete": true,
            "showSaveProgessButton": true
          },
          {
            "name": "company-registered-number",
            "question": "Company Registered Number",
            "titleQuestion": "What is your organisation’s company number?",
            "description": "Description",
            "errorMessage": "Please enter company registered number",
            "fieldType": "gdsTextBox",
            "friendlyFieldName": "Company Registered Number",
            "fieldName": "company-registered-number",
            "mandatory": true,
            "accordianReference": "",
            "maxLength": 8,
            "maxLengthValidationType": "Character",
            "showMarkComplete": true,
            "showSaveProgessButton": true
          },
          {
            "name": "organisation-introduction",
            "question": "Organisation introduction",
            "description": "Description",
            "errorMessage": "Enter organisation proposal",
            "fieldType": "gdsTextArea",
            "friendlyFieldName": "Organisation introduction",
            "fieldName": "organisation-introduction",
            "mandatory": true,
            "accordianReference": "",
            "maxLength": 1000,
            "maxLengthValidationType": "Character",
            "hint": "",
            "showMarkComplete": true,
            "showSaveProgessButton": true
          },
          {
            "name": "type-of-organisation",
            "question": "Type of organisation",
            "titleQuestion": "Which type best describes your organisation?",
            "errorMessage": "Select option",
            "fieldType": "gdsSingleRadioSelectOption",
            "friendlyFieldName": "Type of organisation",
            "fieldName": "type-of-organisation",
            "mandatory": true,
            "accordianReference": "",
            "showMarkComplete": true,
            "hasOtherOption": true,
            "showSaveProgessButton": false,
            "displayQuestionCounter": true,
            "continueButtonText": "Save and continue",
            "selectOptions": [
              "Not for profit",
              "Private company",
              "Public limited company",
              "Public sector organisation",
              "Research organisation",
              "University"
            ]
          },
          {
            "name": "organisation-size",
            "question": "Organisation size",
            "titleQuestion": "What is your organisation's size?",
            "errorMessage": "Select option",
            "fieldType": "gdsSingleRadioSelectOption",
            "friendlyFieldName": "Organisation size",
            "fieldName": "organisation-size",
            "mandatory": true,
            "accordianReference": "",
            "showMarkComplete": true,
            "showSaveProgessButton": false,
            "displayQuestionCounter": true,
            "continueButtonText": "Save and continue",
            "selectOptions": [
              "10 or less employees (micro enterprise)",
              "11 to 50 employees (small enterprise)",
              "51 to 250 employees (medium enterprise)",
              "251 or more employees (large enterprise)"
            ]
          },
          {
            "name": "organisation-maturity",
            "question": "Organisation maturity",
            "titleQuestion": "How old is your organisation?",
            "errorMessage": "Select option",
            "fieldType": "gdsSingleRadioSelectOption",
            "friendlyFieldName": "Organisation maturity",
            "fieldName": "organisation-maturity",
            "mandatory": true,
            "accordianReference": "",
            "showMarkComplete": true,
            "showSaveProgessButton": false,
            "displayQuestionCounter": true,
            "continueButtonText": "Save and continue",
            "selectOptions": [
              "Pre-startup",
              "Startup (less than 1 year)",
              "1 to 5 years",
              "6 to 10 years",
              "11 years or over"
            ]
          },
          {
            "name": "organisation-funding",
            "question": "Organisation funding",
            "titleQuestion": "How is your organisation currently funded?",
            "errorMessage": "Select option",
            "fieldType": "gdsMultiSelect",
            "friendlyFieldName": "Organisation funding",
            "fieldName": "organisation-funding",
            "mandatory": true,
            "accordianReference": "",
            "showMarkComplete": true,
            "showSaveProgessButton": false,
            "displayQuestionCounter": true,
            "continueButtonText": "Save and continue",
            "selectOptions": [
              "No funding",
              "Founders (including bank loans)",
              "Friends and family",
              "Public sector grants",
              "Angel investment",
              "Venture capital",
              "Private equity",
              "Stock market flotation"
            ]
          },
          {
            "name": "parent-organisation",
            "question": "Parent Organisation",
            "titleQuestion": "Do you have a parent organisation?",
            "description": "Description",
            "errorMessage": "Select Yes or No",
            "fieldType": "gdsYesorNoRadio",
            "friendlyFieldName": "Parent Organisation",
            "fieldName": "parent-organisation",
            "mandatory": true,
            "accordianReference": "",
            "showMarkComplete": true,
            "showSaveProgessButton": true,
            "displayQuestionCounter": true
          },
          {
            "name": "parent-organisation-name",
            "question": "Parent organisation Name",
            "description": "Description",
            "errorMessage": "Please enter parent organisation name",
            "fieldType": "gdsTextBox",
            "friendlyFieldName": "Parent organisation Name",
            "fieldName": "parent-organisation-name",
            "mandatory": true,
            "accordianReference": "",
            "maxLength": 50,
            "maxLengthValidationType": "Character",
            "showMarkComplete": true,
            "showSaveProgessButton": true
          },
          {
            "name": "parent-organisation-website",
            "question": "Parent organisation Website",
            "description": "Description",
            "errorMessage": "Please enter parent organisation website",
            "fieldType": "gdsTextBox",
            "friendlyFieldName": "Parent organisation Website",
            "fieldName": "parent-organisation-website",
            "mandatory": true,
            "accordianReference": "",
            "maxLength": 50,
            "maxLengthValidationType": "Character",
            "showMarkComplete": true,
            "showSaveProgessButton": true
          },
          {
            "name": "parent-organisation-address",
            "question": "Parent organisation Address",
            "titleQuestion": "What is your parent organisation's registered address?",
            "description": "Description",
            "errorMessage": "Please enter parent organisation name website",
            "fieldType": "gdsTextBox",
            "friendlyFieldName": "Parent organisation Address",
            "fieldName": "parent-organisation-address",
            "mandatory": true,
            "accordianReference": "",
            "maxLength": 50,
            "maxLengthValidationType": "Character",
            "showMarkComplete": true,
            "showSaveProgessButton": true
          },
          {
            "name": "parent-organisation-size",
            "question": "Parent organisation size",
            "titleQuestion": "What is your parent organisation’s size?",
            "errorMessage": "Select option",
            "fieldType": "gdsSingleRadioSelectOption",
            "friendlyFieldName": "Parent organisation size",
            "fieldName": "parent-organisation-size",
            "mandatory": true,
            "accordianReference": "",
            "showMarkComplete": true,
            "showSaveProgessButton": false,
            "displayQuestionCounter": true,
            "continueButtonText": "Save and continue",
            "selectOptions": [
              "10 or less employees (micro enterprise)",
              "11 to 50 employees (small enterprise)",
              "51 to 250 employees (medium enterprise)",
              "251 or more employees (large enterprise)"
            ]
          },
          {
            "name": "parent-organisation-maturity",
            "question": "Parent organisation maturity",
            "titleQuestion": "How old is your parent organisation?",
            "errorMessage": "Select option",
            "fieldType": "gdsSingleRadioSelectOption",
            "friendlyFieldName": "Parent organisation maturity",
            "fieldName": "parent-organisation-maturity",
            "mandatory": true,
            "accordianReference": "",
            "showMarkComplete": true,
            "showSaveProgessButton": false,
            "displayQuestionCounter": true,
            "continueButtonText": "Save and continue",
            "selectOptions": [
              "Pre-startup",
              "Startup (less than 1 year)",
              "1 to 5 years",
              "6 to 10 years",
              "11 years or over"
            ]
          },
          {
            "name": "parent-recent-turnover",
            "question": "Most recent annual turnover",
            "hint": "The amount of money your business has taken over a period of 12 months.",
            "description": "Description",
            "errorMessage": "Please enter 12 month turnover value",
            "fieldType": "gdsCurrencyBox",
            "friendlyFieldName": "Recent Turnover",
            "fieldName": "parent-recent-turnover",
            "mandatory": true,
            "accordianReference": "",
            "maxLength": 50,
            "maxLengthValidationType": "Character",
            "showMarkComplete": true,
            "showSaveProgessButton": true
          },
          {
            "name": "parent-recent-turnover-date",
            "question": "Most recent turnover date",
            "description": "Description",
            "errorMessage": "Select a valid date",
            "fieldType": "gdsDateBox",
            "friendlyFieldName": "Balance sheet date",
            "fieldName": "parent-balance-sheet-date",
            "mandatory": true,
            "showMarkComplete": true,
            "showSaveProgessButton": true
          },
          {
            "name": "parent-balance-sheet-total",
            "question": "Parent balance sheet total",
            "hint": "Amount, in pounds",
            "description": "Description",
            "errorMessage": "Please enter balance sheet total",
            "fieldType": "gdsCurrencyBox",
            "friendlyFieldName": "Parent balance sheet total",
            "fieldName": "parent-balance-sheet-total",
            "mandatory": true,
            "accordianReference": "",
            "maxLength": 50,
            "maxLengthValidationType": "Character",
            "showMarkComplete": true,
            "showSaveProgessButton": true
          },
          {
            "name": "parent-balance-sheet-date",
            "question": "Parent Balance sheet date",
            "description": "Description",
            "errorMessage": "Select a Valid Date",
            "fieldType": "gdsDateBox",
            "friendlyFieldName": "Parent Balance sheet date",
            "fieldName": "parent-balance-sheet-date",
            "mandatory": true,
            "showMarkComplete": true,
            "showSaveProgessButton": true
          }

        ]
      },
      {
        "title": "Consortium applicant details",
        "overviewTitle": "3. Consortium applicant details",
        "tag": "consortium-applicant",
        "url": "consortium-applicant",
        "ReturnUrl": "application-overview",
        "continueButtonText": "Save and continue",
        "RazorView": "ConsortiumInformation",
        "pages": [
          {
            "name": "consortium-applicant",
            "question": "Are you a sole applicant?",
            "titleQuestion": "Are you a sole applicant?",
            "hint": "If you answer yes, you will return to application overview and this section will be marked as not applicable.",
            "errorMessage": "Select Yes or No",
            "fieldType": "gdsYesorNoRadio",
            "friendlyFieldName": "Consortium Applicant",
            "fieldName": "consortium-applicant",
            "mandatory": true,
            "accordianReference": "",
            "showMarkComplete": false,
            "showSaveProgessButton": false,
            "displayQuestionCounter": true,
            "continueButtonText": "Save and continue",
            "previousPage": {
              "link": "Back to consortium applicants",
              "text": "application-overview"
            },
            "actions": [
              {
                "name": "Yes",
                "value": "1",
                "pageName": "application-overview"
              },
              {
                "name": "No",
                "value": "0",
                "pageName": "consortium-applicant-details"
              }
            ]
          },
          {
            "name": "consortium-applicant-details",
            "question": "Consortium details",
            "titleQuestion": "Consortium details",
            "hint": "Upload your consortium applicant partners details using the form provided in the download section of this page.",
            "errorMessage": "Upload consortium details",
            "fieldType": "gdsFileUpload",
            "friendlyFieldName": "Consortium File Upload",
            "fieldName": "consortium-applicant-details",
            "mandatory": true,
            "accordianReference": "",
            "showMarkComplete": true,
            "showSaveProgessButton": false,
            "filetoDownload": "",
            "displayQuestionCounter": true,
            "continueButtonText": "Save and return to application overview",
            "uploadText": "Upload consortium details"
          }
        ]
      },
      {
        "title": "Proposal Summary",
        "overviewTitle": "4. Proposal summary",
        "tag": "proposal-summary",
        "url": "proposal-summary-overview",
        "returnToSummaryPageLinkText": "Return to the proposal summary overview",
        "continueButtonText": "Save and continue to next question",
        "RazorView": "ProposalSummaryOverview",
        "pages": [
          {
            "name": "project-name",
            "question": "4.1. Project Name",
            "titleQuestion": "4.1. What is the name of your project?",
            "description": "Description",
            "errorMessage": "Please enter a valid project name",
            "fieldType": "gdsTextBox",
            "friendlyFieldName": "Project Name",
            "fieldName": "project-name",
            "mandatory": true,
            "accordianReference": "",
            "maxLength": 50,
            "maxLengthValidationType": "Character",
            "showMarkComplete": true,
            "showSaveProgessButton": true
          },
          {
            "name": "estimated-start-date",
            "question": "4.2. Estimated start date",
            "titleQuestion": "4.2. When do you estimate the project will start?",
            "description": "Description",
            "errorMessage": "Select a Valid Date",
            "fieldType": "gdsDateBox",
            "friendlyFieldName": "Estimated Start Date",
            "fieldName": "estimated-start-date",
            "mandatory": true,
            "showMarkComplete": true,
            "showSaveProgessButton": true
          },
          {
            "name": "estimated-end-date",
            "question": "4.3. Estimated end date",
            "titleQuestion": "4.3. When do you estimate the project will end?",
            "description": "Description",
            "errorMessage": "Select a Valid Date",
            "fieldType": "gdsDateBox",
            "friendlyFieldName": "Estimated End Date",
            "fieldName": "estimated-end-date",
            "mandatory": true,
            "showMarkComplete": true,
            "showSaveProgessButton": true
          },
          {
            "name": "project-location",
            "question": "4.4. Project Location",
            "titleQuestion": "4.4. Will your project be mainly carried out at your organisation's registered address?",
            "description": "Description",
            "errorMessage": "Select Yes or No",
            "fieldType": "gdsYesorNoRadio",
            "friendlyFieldName": "Technology Readiness Level",
            "fieldName": "business-technology-readiness",
            "mandatory": true,
            "accordianReference": "",
            "showMarkComplete": true,
            "showSaveProgessButton": true,
            "displayQuestionCounter": true

          },
          {
            "name": "project-summary",
            "question": "4.5. Project Summary",
            "description": "Description",
            "errorMessage": "Enter project summary details",
            "fieldType": "gdsTextArea",
            "friendlyFieldName": "Project Summary",
            "fieldName": "project-summary",
            "mandatory": true,
            "accordianReference": "",
            "maxLength": 1000,
            "maxLengthValidationType": "Character",
            "hint": "This should be a brief description to help introduce your project to assessors",
            "showMarkComplete": true,
            "showSaveProgessButton": true
          },
          {
            "name": "grant-justification",
            "question": "4.6. Grant Justification",
            "description": "Description",
            "errorMessage": "Enter Grant Justification",
            "fieldType": "gdsTextArea",
            "friendlyFieldName": "Grant Justification",
            "fieldName": "grant-justification",
            "mandatory": true,
            "accordianReference": "",
            "maxLength": 1000,
            "maxLengthValidationType": "Character",
            "hint": "Explain why public sector funding is required to take this concept forward.",
            "showMarkComplete": true,
            "showSaveProgessButton": true
          }
        ]
      },
      {
        "title": "Business Proposal",
        "overviewTitle": "5. Business proposal, project plans and risk",
        "tag": "business-proposal",
        "url": "business-proposal-overview",
        "returnToSummaryPageLinkText": "Return to the business proposal overview",
        "continueButtonText": "Save and continue to next question",
        "RazorView": "BusinessProposalOverview",
        "pages": [
          {
            "name": "business-proposal",
            "question": "5.1. Proposal",
            "description": "Description",
            "errorMessage": "Enter business proposal",
            "fieldType": "gdsTextArea",
            "friendlyFieldName": "Business proposal",
            "fieldName": "business-proposal",
            "mandatory": true,
            "accordianReference": "",
            "maxLength": 1000,
            "maxLengthValidationType": "Word",
            "hint": "",
            "showMarkComplete": true,
            "showSaveProgessButton": true
          },
          {
            "name": "business-plan",
            "question": "5.2. Business Plan",
            "description": "Description",
            "errorMessage": "Enter business plan",
            "fieldType": "gdsTextArea",
            "friendlyFieldName": "Business plan",
            "fieldName": "business-plan",
            "mandatory": true,
            "accordianReference": "",
            "maxLength": 1000,
            "maxLengthValidationType": "Word",
            "showMarkComplete": true,
            "showSaveProgessButton": true
          },
          {
            "name": "business-technology-readiness",
            "question": "5.3. Technology Readiness Level (TRL)",
            "description": "Description",
            "errorMessage": "Enter technology readiness level",
            "fieldType": "gdsTextArea",
            "friendlyFieldName": "Technology Readiness Level",
            "fieldName": "business-technology-readiness",
            "mandatory": true,
            "accordianReference": "",
            "maxLength": 1000,
            "maxLengthValidationType": "Word",
            "showMarkComplete": true,
            "showSaveProgessButton": true
          },
          {
            "name": "business-technology-readiness-document",
            "question": "5.3.1 Upload Technology Readiness Level (TRL)",
            "titleQuestion": "Upload Technology Readiness Level (TRL)",
            "hint": "",
            "errorMessage": "Upload technology readiness level",
            "fieldType": "gdsFileUpload",
            "friendlyFieldName": "Consortium File Upload",
            "fieldName": "business-technology-readiness-document",
            "mandatory": true,
            "accordianReference": "",
            "showMarkComplete": true,
            "showSaveProgessButton": false,
            "filetoDownload": "",
            "displayQuestionCounter": true,
            "uploadText": "Upload Technology Readiness Level"
          },
          {
            "name": "business-infrastructure",
            "question": "5.4. Infrastructure",
            "description": "Description",
            "errorMessage": "Enter infrastructure",
            "fieldType": "gdsTextArea",
            "friendlyFieldName": "Infrastructure",
            "fieldName": "business-infrastructure",
            "mandatory": true,
            "accordianReference": "",
            "maxLength": 1000,
            "maxLengthValidationType": "Word",
            "hint": "You should include evidence where you can.",
            "showMarkComplete": true,
            "showSaveProgessButton": true
          },
          {
            "name": "business-environmental-impact",
            "question": "5.5. Environmental impact",
            "description": "Description",
            "errorMessage": "Enter environmental impact",
            "fieldType": "gdsTextArea",
            "friendlyFieldName": "Environmental impact",
            "fieldName": "business-environmental-impact",
            "mandatory": true,
            "accordianReference": "",
            "maxLength": 1000,
            "maxLengthValidationType": "Word",
            "showMarkComplete": true,
            "showSaveProgessButton": true
          },
          {
            "name": "business-regulations",
            "question": "5.6. Regulations",
            "description": "Description",
            "errorMessage": "Enter regulations",
            "fieldType": "gdsTextArea",
            "friendlyFieldName": "Regulations",
            "fieldName": "business-regulations",
            "mandatory": true,
            "accordianReference": "",
            "maxLength": 1000,
            "maxLengthValidationType": "Word",
            "showMarkComplete": true,
            "showSaveProgessButton": true
          },
          {
            "name": "business-impact-on-climate-change",
            "question": "5.7. Impact on climate change",
            "description": "Description",
            "errorMessage": "Enter impact on climate change",
            "fieldType": "gdsTextArea",
            "friendlyFieldName": "Impact on climate change",
            "fieldName": "business-impact-on-climate-change",
            "mandatory": true,
            "accordianReference": "",
            "maxLength": 1000,
            "maxLengthValidationType": "Word",
            "hint": "Use scientific studies and research to prove your claims where you can.",
            "showMarkComplete": true,
            "showSaveProgessButton": true
          },
          {
            "name": "business-project-plan",
            "question": "5.8. Project plan",
            "description": "Description",
            "errorMessage": "Enter project plan",
            "fieldType": "gdsTextArea",
            "friendlyFieldName": "Project plan",
            "fieldName": "business-project-plan",
            "mandatory": true,
            "accordianReference": "",
            "maxLength": 1000,
            "maxLengthValidationType": "Word",
            "hint": "Use scientific studies and research to prove your claims where you can.",
            "showMarkComplete": true,
            "showSaveProgessButton": true
          },
          {
            "name": "business-project-plan-document",
            "question": "5.8.1 Upload project plan",
            "titleQuestion": "Upload project plan",
            "hint": "",
            "errorMessage": "Upload project plan",
            "fieldType": "gdsFileUpload",
            "friendlyFieldName": "Project Plan File Upload",
            "fieldName": "business-project-plan-document",
            "mandatory": true,
            "accordianReference": "",
            "showMarkComplete": true,
            "showSaveProgessButton": false,
            "filetoDownload": "",
            "displayQuestionCounter": true,
            "uploadText": "Upload project plan"
          },
          {
            "name": "business-project-evaluation",
            "question": "5.9. Project evaluation",
            "description": "Description",
            "errorMessage": "Enter project evaluation",
            "fieldType": "gdsTextArea",
            "friendlyFieldName": "Project evaluation",
            "fieldName": "business-project-evaluation",
            "mandatory": true,
            "accordianReference": "",
            "maxLength": 1000,
            "maxLengthValidationType": "Word",
            "hint": "",
            "showMarkComplete": true,
            "showSaveProgessButton": true
          },
          {
            "name": "business-project-evaluation-document",
            "question": "5.9.1 Upload project evaluation",
            "titleQuestion": "Upload project evaluation",
            "hint": "",
            "errorMessage": "Upload project evaluation",
            "fieldType": "gdsFileUpload",
            "friendlyFieldName": "Project Evaluation File Upload",
            "fieldName": "business-project-plan-document",
            "mandatory": true,
            "accordianReference": "",
            "showMarkComplete": true,
            "showSaveProgessButton": false,
            "filetoDownload": "",
            "displayQuestionCounter": true,
            "uploadText": "Upload project evaluation"
          },
          {
            "name": "business-skills-and-experience",
            "question": "5.10. Skills and experience",
            "description": "Description",
            "errorMessage": "Enter skills and experience",
            "fieldType": "gdsTextArea",
            "friendlyFieldName": "Skills and experience",
            "fieldName": "business-skills-and-experience",
            "mandatory": true,
            "accordianReference": "",
            "maxLength": 1000,
            "maxLengthValidationType": "Word",
            "hint": "",
            "showMarkComplete": true,
            "showSaveProgessButton": true
          },
          {
            "name": "business-skills-and-experience-document",
            "question": "5.10.1 Upload skills and experience",
            "titleQuestion": "5.10.1 Upload skills and experience",
            "errorMessage": "Upload skills and experience",
            "fieldType": "gdsFileUpload",
            "friendlyFieldName": "Skills and experience File Upload",
            "fieldName": "business-skills-and-experience-document",
            "mandatory": true,
            "accordianReference": "",
            "showMarkComplete": true,
            "showSaveProgessButton": false,
            "hint": "You can upload a document which highlights your team's experience and skills in greater detail:",
            "filetoDownload": "",
            "displayQuestionCounter": true,
            "uploadText": "Upload project evaluation"
          },
          {
            "name": "business-letter-of-support-document",
            "question": "5.11. Letter of support (optional)",
            "titleQuestion": "5.11. Letter of support (optional)",
            "hint": "",
            "errorMessage": "Upload a Letter of support",
            "fieldType": "gdsFileUpload",
            "friendlyFieldName": "Letter of support File Upload",
            "fieldName": "business-letter-of-support-document",
            "mandatory": true,
            "accordianReference": "",
            "showMarkComplete": true,
            "showSaveProgessButton": false,
            "filetoDownload": "",
            "displayQuestionCounter": true,
            "uploadText": "Upload a Letter of support"
          }
        ]
      },
      {
        "title": "Finance Proposal",
        "overviewTitle": "6. Financial proposal and costs",
        "tag": "finance-proposal",
        "url": "finance-proposal-overview",
        "returnToSummaryPageLinkText": "Return to the finance proposal overview",
        "continueButtonText": "Save and continue to next question",
        "RazorView": "FinanceProposalOverview",
        "pages": [
          {
            "name": "project-cost-breakdown",
            "question": "6.2. Project cost breakdown",
            "titleQuestion": "6.2 Project cost breakdown",
            "description": "Provide a breakdown of your costs using the template provided in the download section of this page.",
            "errorMessage": "Please provide a breakdown of your costs",
            "fieldType": "gdsFileUpload",
            "friendlyFieldName": "Project Cost Breakdown",
            "fieldName": "project-cost-breakdown",
            "mandatory": true,
            "accordianReference": "",
            "maxLength": 50,
            "maxLengthValidationType": "Character",
            "showMarkComplete": true,
            "showSaveProgessButton": true
          },
          {
            "name": "financial-background",
            "question": "6.3. Financial background",
            "titleQuestion": "6.3. Financial background",
            "description": "You can give extra details about the information you enter on the Finance Spreadsheet here.",
            "errorMessage": "Please provide a summary of your financial background",
            "fieldType": "gdsTextArea",
            "friendlyFieldName": "Financial Background",
            "fieldName": "financial-background",
            "maxLength": 500,
            "maxLengthValidationType": "Word",
            "mandatory": true,
            "showMarkComplete": true,
            "showSaveProgessButton": true
          },
          {
            "name": "in-kind-contributions",
            "question": "6.4. In-kind contributions",
            "titleQuestion": "6.4. In-kind contributions",
            "description": "In-kind contributions are valuable items or services which you don't need to pay for during your project.",
            "errorMessage": "Please provide a summary of your in-kind contributions",
            "fieldType": "gdsTextArea",
            "friendlyFieldName": "In-kind Contributions",
            "maxLength": 200,
            "maxLengthValidationType": "Word",
            "fieldName": "in-kind-contributions",
            "mandatory": true,
            "showMarkComplete": true,
            "showSaveProgessButton": true
          }
        ]
      },
      {
        "title": "Performance data",
        "overviewTitle": "7. Performance data",
        "tag": "performance-data",
        "url": "performance-data",
        "continueButtonText": "Save and continue",
        "RazorView": "PerformanceData",
        "pages": [
        ]
      }
    ]
  }
}
